{
  "id" : "default",
  "version": "0.0.1",
  "options": [
    {"name": "maxNumOfLines", "type": "number", "default": 10},
    {"name": "hasChatInput", "type": "toggle", "default": false},
    {"name": "bgColor", "type": "color", "default":"black"},
    {"name": "textColor", "type" : "color", "default": "white"},
    {"name": "userColor", "type": "color"},
    {"name": "sysColor", "type": "color", "default": "#ffcccc"},
    {"name": "useUserCustomColor", "type": "toggle", "default": true},
    {"name": "clearBannedMsg", "type": "toggle", "default": true},
    {"name": "allowClearChat", "type": "toggle", "default": true}
  ]
}
